Workbook
Name Button_429: "LeaseCalc_Lease_Data_List"
Name CellAbove: INDIRECT(ADDRESS(ROW()-1,COLUMN()))
Name CIT: #N/A
Name IQ_CH: 110000
Name IQ_CQ: 5000
Name IQ_CY: 10000
Name IQ_DAILY: 500000
Name IQ_FH: 100000
Name IQ_FQ: 500
Name IQ_FY: 1000
Name IQ_LTM: 2000
Name IQ_MONTH: 15000
Name IQ_NTM: 6000
Name IQ_WEEK: 50000
Name IQ_YTD: 3000
Name TM1REBUILDOPTION: 1

Sheet Control | Setup
A1: Control | Setup
A2: Central template controls and metadata for any deal.
A4: Template Note | B4: Pack A scaffold only: direct formulas/values, no Excel Tables, no required named ranges.
A7: Field | B7: Value
A8: Engagement / Target
A9: TemplateVersion | B9: v1.0-packA
A10: Currency | B10: USD
A11: Units | B11: $000s
A12: FYEndMonth (1-12) | B12: 12
A13: LatestMonthEnd
A14: LastRefreshTime
A15: PreparedBy
A16: ReviewedBy
A17: Notes

Sheet Control | Periods
A1: Control | Periods
A2: Period engine block used by all output tabs (plain range, anchored).
A4: Template Note | B4: Pack A scaffold only: direct formulas/values, no Excel Tables, no required named ranges.
A8: PeriodEndDate | B8: PeriodKey | C8: Label_Flow | D8: Label_Snapshot | E8: FY | F8: IsFYEnd | G8: IsInLast36M | H8: IsTTMEnd | I8: SortOrder
B9: =IF(A9="","",TEXT(A9,"yyyymm")) | C9: =IF(A9="","",TEXT(A9,"mmm-yy")) | D9: =IF(A9="","",TEXT(A9,"mmm-yy")) | E9: =IF(A9="","",YEAR(A9)+(MONTH(A9)>'Control | Setup'!$B$12)) | F9: =IF(A9="","",MONTH(A9)='Control | Setup'!$B$12) | G9: =IF(OR(A9="",'Control | Setup'!$B$13=""),"",AND(A9<='Control | Setup'!$B$13,A9>EOMONTH('Control | Setup'!$B$13,-36))) | H9: =IF(OR(A9="",'Control | Setup'!$B$13=""),"",A9='Control | Setup'!$B$13) | I9: =IF(A9="","",ROW()-8)
B10: =IF(A10="","",TEXT(A10,"yyyymm")) | C10: =IF(A10="","",TEXT(A10,"mmm-yy")) | D10: =IF(A10="","",TEXT(A10,"mmm-yy")) | E10: =IF(A10="","",YEAR(A10)+(MONTH(A10)>'Control | Setup'!$B$12)) | F10: =IF(A10="","",MONTH(A10)='Control | Setup'!$B$12) | G10: =IF(OR(A10="",'Control | Setup'!$B$13=""),"",AND(A10<='Control | Setup'!$B$13,A10>EOMONTH('Control | Setup'!$B$13,-36))) | H10: =IF(OR(A10="",'Control | Setup'!$B$13=""),"",A10='Control | Setup'!$B$13) | I10: =IF(A10="","",ROW()-8)
B11: =IF(A11="","",TEXT(A11,"yyyymm")) | C11: =IF(A11="","",TEXT(A11,"mmm-yy")) | D11: =IF(A11="","",TEXT(A11,"mmm-yy")) | E11: =IF(A11="","",YEAR(A11)+(MONTH(A11)>'Control | Setup'!$B$12)) | F11: =IF(A11="","",MONTH(A11)='Control | Setup'!$B$12) | G11: =IF(OR(A11="",'Control | Setup'!$B$13=""),"",AND(A11<='Control | Setup'!$B$13,A11>EOMONTH('Control | Setup'!$B$13,-36))) | H11: =IF(OR(A11="",'Control | Setup'!$B$13=""),"",A11='Control | Setup'!$B$13) | I11: =IF(A11="","",ROW()-8)
B12: =IF(A12="","",TEXT(A12,"yyyymm")) | C12: =IF(A12="","",TEXT(A12,"mmm-yy")) | D12: =IF(A12="","",TEXT(A12,"mmm-yy")) | E12: =IF(A12="","",YEAR(A12)+(MONTH(A12)>'Control | Setup'!$B$12)) | F12: =IF(A12="","",MONTH(A12)='Control | Setup'!$B$12) | G12: =IF(OR(A12="",'Control | Setup'!$B$13=""),"",AND(A12<='Control | Setup'!$B$13,A12>EOMONTH('Control | Setup'!$B$13,-36))) | H12: =IF(OR(A12="",'Control | Setup'!$B$13=""),"",A12='Control | Setup'!$B$13) | I12: =IF(A12="","",ROW()-8)
B13: =IF(A13="","",TEXT(A13,"yyyymm")) | C13: =IF(A13="","",TEXT(A13,"mmm-yy")) | D13: =IF(A13="","",TEXT(A13,"mmm-yy")) | E13: =IF(A13="","",YEAR(A13)+(MONTH(A13)>'Control | Setup'!$B$12)) | F13: =IF(A13="","",MONTH(A13)='Control | Setup'!$B$12) | G13: =IF(OR(A13="",'Control | Setup'!$B$13=""),"",AND(A13<='Control | Setup'!$B$13,A13>EOMONTH('Control | Setup'!$B$13,-36))) | H13: =IF(OR(A13="",'Control | Setup'!$B$13=""),"",A13='Control | Setup'!$B$13) | I13: =IF(A13="","",ROW()-8)
B14: =IF(A14="","",TEXT(A14,"yyyymm")) | C14: =IF(A14="","",TEXT(A14,"mmm-yy")) | D14: =IF(A14="","",TEXT(A14,"mmm-yy")) | E14: =IF(A14="","",YEAR(A14)+(MONTH(A14)>'Control | Setup'!$B$12)) | F14: =IF(A14="","",MONTH(A14)='Control | Setup'!$B$12) | G14: =IF(OR(A14="",'Control | Setup'!$B$13=""),"",AND(A14<='Control | Setup'!$B$13,A14>EOMONTH('Control | Setup'!$B$13,-36))) | H14: =IF(OR(A14="",'Control | Setup'!$B$13=""),"",A14='Control | Setup'!$B$13) | I14: =IF(A14="","",ROW()-8)
B15: =IF(A15="","",TEXT(A15,"yyyymm")) | C15: =IF(A15="","",TEXT(A15,"mmm-yy")) | D15: =IF(A15="","",TEXT(A15,"mmm-yy")) | E15: =IF(A15="","",YEAR(A15)+(MONTH(A15)>'Control | Setup'!$B$12)) | F15: =IF(A15="","",MONTH(A15)='Control | Setup'!$B$12) | G15: =IF(OR(A15="",'Control | Setup'!$B$13=""),"",AND(A15<='Control | Setup'!$B$13,A15>EOMONTH('Control | Setup'!$B$13,-36))) | H15: =IF(OR(A15="",'Control | Setup'!$B$13=""),"",A15='Control | Setup'!$B$13) | I15: =IF(A15="","",ROW()-8)
B16: =IF(A16="","",TEXT(A16,"yyyymm")) | C16: =IF(A16="","",TEXT(A16,"mmm-yy")) | D16: =IF(A16="","",TEXT(A16,"mmm-yy")) | E16: =IF(A16="","",YEAR(A16)+(MONTH(A16)>'Control | Setup'!$B$12)) | F16: =IF(A16="","",MONTH(A16)='Control | Setup'!$B$12) | G16: =IF(OR(A16="",'Control | Setup'!$B$13=""),"",AND(A16<='Control | Setup'!$B$13,A16>EOMONTH('Control | Setup'!$B$13,-36))) | H16: =IF(OR(A16="",'Control | Setup'!$B$13=""),"",A16='Control | Setup'!$B$13) | I16: =IF(A16="","",ROW()-8)
B17: =IF(A17="","",TEXT(A17,"yyyymm")) | C17: =IF(A17="","",TEXT(A17,"mmm-yy")) | D17: =IF(A17="","",TEXT(A17,"mmm-yy")) | E17: =IF(A17="","",YEAR(A17)+(MONTH(A17)>'Control | Setup'!$B$12)) | F17: =IF(A17="","",MONTH(A17)='Control | Setup'!$B$12) | G17: =IF(OR(A17="",'Control | Setup'!$B$13=""),"",AND(A17<='Control | Setup'!$B$13,A17>EOMONTH('Control | Setup'!$B$13,-36))) | H17: =IF(OR(A17="",'Control | Setup'!$B$13=""),"",A17='Control | Setup'!$B$13) | I17: =IF(A17="","",ROW()-8)
B18: =IF(A18="","",TEXT(A18,"yyyymm")) | C18: =IF(A18="","",TEXT(A18,"mmm-yy")) | D18: =IF(A18="","",TEXT(A18,"mmm-yy")) | E18: =IF(A18="","",YEAR(A18)+(MONTH(A18)>'Control | Setup'!$B$12)) | F18: =IF(A18="","",MONTH(A18)='Control | Setup'!$B$12) | G18: =IF(OR(A18="",'Control | Setup'!$B$13=""),"",AND(A18<='Control | Setup'!$B$13,A18>EOMONTH('Control | Setup'!$B$13,-36))) | H18: =IF(OR(A18="",'Control | Setup'!$B$13=""),"",A18='Control | Setup'!$B$13) | I18: =IF(A18="","",ROW()-8)
B19: =IF(A19="","",TEXT(A19,"yyyymm")) | C19: =IF(A19="","",TEXT(A19,"mmm-yy")) | D19: =IF(A19="","",TEXT(A19,"mmm-yy")) | E19: =IF(A19="","",YEAR(A19)+(MONTH(A19)>'Control | Setup'!$B$12)) | F19: =IF(A19="","",MONTH(A19)='Control | Setup'!$B$12) | G19: =IF(OR(A19="",'Control | Setup'!$B$13=""),"",AND(A19<='Control | Setup'!$B$13,A19>EOMONTH('Control | Setup'!$B$13,-36))) | H19: =IF(OR(A19="",'Control | Setup'!$B$13=""),"",A19='Control | Setup'!$B$13) | I19: =IF(A19="","",ROW()-8)
B20: =IF(A20="","",TEXT(A20,"yyyymm")) | C20: =IF(A20="","",TEXT(A20,"mmm-yy")) | D20: =IF(A20="","",TEXT(A20,"mmm-yy")) | E20: =IF(A20="","",YEAR(A20)+(MONTH(A20)>'Control | Setup'!$B$12)) | F20: =IF(A20="","",MONTH(A20)='Control | Setup'!$B$12) | G20: =IF(OR(A20="",'Control | Setup'!$B$13=""),"",AND(A20<='Control | Setup'!$B$13,A20>EOMONTH('Control | Setup'!$B$13,-36))) | H20: =IF(OR(A20="",'Control | Setup'!$B$13=""),"",A20='Control | Setup'!$B$13) | I20: =IF(A20="","",ROW()-8)
... B128: =IF(A128="","",TEXT(A128,"yyyymm")) | C128: =IF(A128="","",TEXT(A128,"mmm-yy")) | D128: =IF(A128="","",TEXT(A128,"mmm-yy")) | E128: =IF(A128="","",YEAR(A128)+(MONTH(A128)>'Control | Setup'!$B$12)) | F128: =IF(A128="","",MONTH(A128)='Control | Setup'!$B$12) | G128: =IF(OR(A128="",'Control | Setup'!$B$13=""),"",AND(A128<='Control | Setup'!$B$13,A128>EOMONTH('Control | Setup'!$B$13,-36))) | H128: =IF(OR(A128="",'Control | Setup'!$B$13=""),"",A128='Control | Setup'!$B$13) | I128: =IF(A128="","",ROW()-8)

Sheet Template | Manifest
A1: Template | Manifest
A2: Module registry the generator can read deterministically.
A4: Template Note | B4: Pack A scaffold only: direct formulas/values, no Excel Tables, no required named ranges.
A8: ModuleKey | B8: ModuleName | C8: SheetNames | D8: Purpose | E8: PrimaryInputs | F8: Dependencies | G8: TypicalUseCases | H8: CanInstantiateMultiple
A9: CORE_CONTROLS | B9: Controls | C9: Control | Setup; Control | Periods; Control | QC | D9: Template controls and QC center | E9: Manual setup | F9: None | G9: All deals | H9: FALSE
A10: CORE_DATA | B10: Data intake | C10: Data | TB (Wide); Data | AR Aging; Data | AP Aging | D10: Standardized data ingestion blocks | E10: Client exports | F10: Control | Periods | G10: All deals | H10: FALSE
A11: CORE_MAPPING | B11: Mappings | C11: Map | COA to Lines; Map | NWC & NetDebt Class; Map | Entities | D11: Account and classification mappings | E11: TB + team mapping decisions | F11: Data | TB (Wide) | G11: All deals | H11: FALSE
A12: CORE_FINANCIALS | B12: Financial statements | C12: Financials>>; Combined | IS; Combined | BS; Combined | CF; Entity 1 | IS; Entity 1 | BS; Entity 1 | CF | D12: Core financial statement scaffolds for combined and placeholder entity views | E12: Control | Periods; Data | TB (Wide); Map | COA to Lines | F12: Pack A tabs | G12: All deals | H12: TRUE

Sheet Template | Index
A1: Template | Index
A2: Deterministic block coordinate index (fixed anchors, no named ranges required).
A4: Template Note | B4: Pack A scaffold only: direct formulas/values, no Excel Tables, no required named ranges.
A8: SheetName | B8: BlockKey | C8: TopLeftCell | D8: HeaderRowNumber | E8: FirstDataRowNumber | F8: PeriodStartColumn | G8: PeriodHeaderRowNumber | H8: NotesPanelTopLeftCell | I8: OutputType | J8: RefreshRequired | K8: ValidationRule
A9: Control | Setup | B9: CONTROL_SETUP_FIELDS | C9: A7 | D9: 7 | E9: 8 | I9: grid | J9: FALSE | K9: FYEndMonth in B12; LatestMonthEnd in B13
A10: Control | Periods | B10: PERIODS_BLOCK | C10: A8 | D10: 8 | E10: 9 | F10: A | G10: 8 | I10: grid | J10: FALSE | K10: A9:A128 must be month-end dates
A11: Template | Manifest | B11: MANIFEST_MAIN | C11: A8 | D11: 8 | E11: 9 | I11: grid | J11: FALSE | K11: Module keys should be stable
A12: Template | Index | B12: INDEX_MAIN | C12: A8 | D12: 8 | E12: 9 | I12: grid | J12: FALSE | K12: Update when block anchors move
A13: Data | TB (Wide) | B13: TB_WIDE_INPUT | C13: A8 | D13: 8 | E13: 9 | F13: G | G13: 8 | I13: grid | J13: FALSE | K13: Month columns map to Control | Periods A9:A44
A14: Data | AR Aging | B14: AR_AGING_INPUT | C14: A8 | D14: 8 | E14: 9 | I14: grid | J14: FALSE | K14: Total column should equal bucket sum
A15: Data | AP Aging | B15: AP_AGING_INPUT | C15: A8 | D15: 8 | E15: 9 | I15: grid | J15: FALSE | K15: Total column should equal bucket sum
A16: Map | COA to Lines | B16: COA_MAP_INPUT | C16: A8 | D16: 8 | E16: 9 | I16: grid | J16: FALSE | K16: LineKey values must be stable
A17: Map | NWC & NetDebt Class | B17: CLASS_MAP_INPUT | C17: A8 | D17: 8 | E17: 9 | I17: grid | J17: FALSE | K17: ClassKey values must be stable
A18: Map | Entities | B18: ENTITIES_MAP_INPUT | C18: A8 | D18: 8 | E18: 9 | I18: grid | J18: FALSE | K18: SortOrder should be sequential
A19: Financials>> | B19: FINANCIALS_DIVIDER | C19: A1 | D19: 1 | E19: 4 | I19: grid | J19: FALSE | K19: Navigation links should point to Pack B sheets
A20: Combined | IS | B20: IS_MAIN | C20: A8 | D20: 8 | E20: 9 | F20: F | G20: 8 | I20: grid | J20: FALSE | K20: Monthly headers link to Control | Periods
A21: Combined | IS | B21: IS_CHECKS | C21: A27 | D21: 27 | E21: 28 | F21: F | G21: 8 | I21: grid | J21: FALSE | K21: Check values should resolve to 0
A22: Combined | BS | B22: BS_MAIN | C22: A8 | D22: 8 | E22: 9 | F22: F | G22: 8 | I22: grid | J22: FALSE | K22: Monthly headers link to Control | Periods
A23: Combined | BS | B23: BS_CHECKS | C23: A27 | D23: 27 | E23: 28 | F23: F | G23: 8 | I23: grid | J23: FALSE | K23: Balance check should resolve to 0
A24: Combined | CF | B24: CF_MAIN | C24: A8 | D24: 8 | E24: 9 | F24: F | G24: 8 | I24: grid | J24: FALSE | K24: Monthly headers link to Control | Periods
A25: Combined | CF | B25: CF_CHECKS | C25: A27 | D25: 27 | E25: 28 | F25: F | G25: 8 | I25: grid | J25: FALSE | K25: Check values should resolve to 0
A26: Entity 1 | IS | B26: ENTITY1_IS_MAIN | C26: A8 | D26: 8 | E26: 9 | F26: F | G26: 8 | I26: grid | J26: FALSE | K26: Entity placeholder scaffold
A27: Entity 1 | BS | B27: ENTITY1_BS_MAIN | C27: A8 | D27: 8 | E27: 9 | F27: F | G27: 8 | I27: grid | J27: FALSE | K27: Entity placeholder scaffold
A28: Entity 1 | CF | B28: ENTITY1_CF_MAIN | C28: A8 | D28: 8 | E28: 9 | F28: F | G28: 8 | I28: grid | J28: FALSE | K28: Entity placeholder scaffold

Sheet Data | TB (Wide)
A1: Data | TB (Wide)
A2: Load monthly trial balance in wide format. Do not insert/delete month columns manually.
A4: Template Note | B4: Pack A scaffold only: direct formulas/values, no Excel Tables, no required named ranges.
A8: Entity | B8: AccountNumber | C8: AccountName | D8: FS_SignConvention | E8: Currency | F8: SourceSystem | G8: ='Control | Periods'!A9 | H8: ='Control | Periods'!A10 | I8: ='Control | Periods'!A11 | J8: ='Control | Periods'!A12 | K8: ='Control | Periods'!A13 | L8: ='Control | Periods'!A14 | M8: ='Control | Periods'!A15 | N8: ='Control | Periods'!A16 | O8: ='Control | Periods'!A17 | P8: ='Control | Periods'!A18 | Q8: ='Control | Periods'!A19 | R8: ='Control | Periods'!A20 | S8: ='Control | Periods'!A21 | T8: ='Control | Periods'!A22 | U8: ='Control | Periods'!A23 | V8: ='Control | Periods'!A24 | W8: ='Control | Periods'!A25 | X8: ='Control | Periods'!A26 | Y8: ='Control | Periods'!A27 | Z8: ='Control | Periods'!A28 | AA8: ='Control | Periods'!A29 | AB8: ='Control | Periods'!A30 | AC8: ='Control | Periods'!A31 | AD8: ='Control | Periods'!A32 | AE8: ='Control | Periods'!A33 | AF8: ='Control | Periods'!A34 | AG8: ='Control | Periods'!A35 | AH8: ='Control | Periods'!A36 | AI8: ='Control | Periods'!A37 | AJ8: ='Control | Periods'!A38 | AK8: ='Control | Periods'!A39 | AL8: ='Control | Periods'!A40 | AM8: ='Control | Periods'!A41 | AN8: ='Control | Periods'!A42 | AO8: ='Control | Periods'!A43 | AP8: ='Control | Periods'!A44 | AQ8: FY-2 | AR8: FY-1 | AS8: TTM

Sheet Data | AR Aging
A1: Data | AR Aging
A2: Canonical aging input block with fixed buckets and total check.
A4: Template Note | B4: Pack A scaffold only: direct formulas/values, no Excel Tables, no required named ranges.
A8: AsAtDate | B8: Entity | C8: CounterpartyName | D8: CounterpartyID | E8: Current | F8: 1-30 | G8: 31-60 | H8: 61-90 | I8: 91-120 | J8: >120 | K8: Total
K9: =IF(A9="","",SUM(E9:J9))
K10: =IF(A10="","",SUM(E10:J10))
K11: =IF(A11="","",SUM(E11:J11))
K12: =IF(A12="","",SUM(E12:J12))
K13: =IF(A13="","",SUM(E13:J13))
K14: =IF(A14="","",SUM(E14:J14))
K15: =IF(A15="","",SUM(E15:J15))
K16: =IF(A16="","",SUM(E16:J16))
K17: =IF(A17="","",SUM(E17:J17))
K18: =IF(A18="","",SUM(E18:J18))
K19: =IF(A19="","",SUM(E19:J19))
K20: =IF(A20="","",SUM(E20:J20))
... K508: =IF(A508="","",SUM(E508:J508))

Sheet Data | AP Aging
A1: Data | AP Aging
A2: Canonical aging input block with fixed buckets and total check.
A4: Template Note | B4: Pack A scaffold only: direct formulas/values, no Excel Tables, no required named ranges.
A8: AsAtDate | B8: Entity | C8: CounterpartyName | D8: CounterpartyID | E8: Current | F8: 1-30 | G8: 31-60 | H8: 61-90 | I8: 91-120 | J8: >120 | K8: Total
K9: =IF(A9="","",SUM(E9:J9))
K10: =IF(A10="","",SUM(E10:J10))
K11: =IF(A11="","",SUM(E11:J11))
K12: =IF(A12="","",SUM(E12:J12))
K13: =IF(A13="","",SUM(E13:J13))
K14: =IF(A14="","",SUM(E14:J14))
K15: =IF(A15="","",SUM(E15:J15))
K16: =IF(A16="","",SUM(E16:J16))
K17: =IF(A17="","",SUM(E17:J17))
K18: =IF(A18="","",SUM(E18:J18))
K19: =IF(A19="","",SUM(E19:J19))
K20: =IF(A20="","",SUM(E20:J20))
... K508: =IF(A508="","",SUM(E508:J508))

Sheet Map | COA to Lines
A1: Map | COA to Lines
A2: Map source accounts to reporting lines used by FS/QofE scaffolds.
A4: Template Note | B4: Pack A scaffold only: direct formulas/values, no Excel Tables, no required named ranges.
A8: AccountNumber | B8: AccountName | C8: Statement | D8: LineKey | E8: LineName | F8: GroupKey | G8: SortOrder | H8: SignMultiplier | I8: Notes

Sheet Map | NWC & NetDebt Class
A1: Map | NWC & NetDebt Class
A2: Classification mapping for NWC, Net debt, and Stratified BS views.
A4: Template Note | B4: Pack A scaffold only: direct formulas/values, no Excel Tables, no required named ranges.
A8: AccountNumber | B8: ClassType | C8: ClassKey | D8: ClassName | E8: Bucket | F8: WorkingCapitalFlag | G8: NetDebtFlag | H8: SortOrder

Sheet Map | Entities
A1: Map | Entities
A2: Entity list and ordering controls used by combined/entity views.
A4: Template Note | B4: Pack A scaffold only: direct formulas/values, no Excel Tables, no required named ranges.
A8: EntityName | B8: EntityCode | C8: IncludeFlag | D8: SortOrder | E8: Notes

Sheet Financials>>
A1: Financials>>
A2: Navigation divider for financial statement scaffolds.
A4: =HYPERLINK("#'Combined | IS'!A1","Go to Combined | IS")
A5: =HYPERLINK("#'Combined | BS'!A1","Go to Combined | BS")
A6: =HYPERLINK("#'Combined | CF'!A1","Go to Combined | CF")
A7: =HYPERLINK("#'Entity 1 | IS'!A1","Go to Entity 1 | IS")
A8: =HYPERLINK("#'Entity 1 | BS'!A1","Go to Entity 1 | BS")
A9: =HYPERLINK("#'Entity 1 | CF'!A1","Go to Entity 1 | CF")

Sheet Combined | IS
A1: Combined | IS (Template Scaffold)
A2: Combined IS scaffold with deterministic anchors and check block.
A4: Data as of | D4: Units | E4: ='Control | Setup'!B11
A5: Version | B5: ='Control | Setup'!B9 | D5: Last refresh | E5: ='Control | Setup'!B14
A8: LineKey | B8: LineName | C8: Sign | D8: Source | E8: Comments | F8: ='Control | Periods'!A9 | G8: ='Control | Periods'!A10 | H8: ='Control | Periods'!A11 | I8: ='Control | Periods'!A12 | J8: ='Control | Periods'!A13 | K8: ='Control | Periods'!A14 | L8: ='Control | Periods'!A15 | M8: ='Control | Periods'!A16 | N8: ='Control | Periods'!A17 | O8: ='Control | Periods'!A18 | P8: ='Control | Periods'!A19 | Q8: ='Control | Periods'!A20 | R8: ='Control | Periods'!A21 | S8: ='Control | Periods'!A22 | T8: ='Control | Periods'!A23 | U8: ='Control | Periods'!A24 | V8: ='Control | Periods'!A25 | W8: ='Control | Periods'!A26 | X8: ='Control | Periods'!A27 | Y8: ='Control | Periods'!A28 | Z8: ='Control | Periods'!A29 | AA8: ='Control | Periods'!A30 | AB8: ='Control | Periods'!A31 | AC8: ='Control | Periods'!A32 | AD8: ='Control | Periods'!A33 | AE8: ='Control | Periods'!A34 | AF8: ='Control | Periods'!A35 | AG8: ='Control | Periods'!A36 | AH8: ='Control | Periods'!A37 | AI8: ='Control | Periods'!A38 | AJ8: ='Control | Periods'!A39 | AK8: ='Control | Periods'!A40 | AL8: ='Control | Periods'!A41 | AM8: ='Control | Periods'!A42 | AN8: ='Control | Periods'!A43 | AO8: ='Control | Periods'!A44 | AP8: FY-2 | AQ8: FY-1 | AR8: TTM
A9: IS_REV | B9: Revenue | C9: + | D9: TB/Map | AP9: =IF(COUNT(F9:Q9)=0,"",SUM(F9:Q9)) | AQ9: =IF(COUNT(R9:AC9)=0,"",SUM(R9:AC9)) | AR9: =IF(COUNT(AD9:AO9)=0,"",SUM(AD9:AO9))
A10: IS_COGS | B10: Cost of goods sold | C10: + | D10: TB/Map | AP10: =IF(COUNT(F10:Q10)=0,"",SUM(F10:Q10)) | AQ10: =IF(COUNT(R10:AC10)=0,"",SUM(R10:AC10)) | AR10: =IF(COUNT(AD10:AO10)=0,"",SUM(AD10:AO10))
A11: IS_GP | B11: Gross profit | C11: + | D11: Formula | E11: Derived | F11: =IF(OR(F9="",F10=""),"",F9+F10) | G11: =IF(OR(G9="",G10=""),"",G9+G10) | H11: =IF(OR(H9="",H10=""),"",H9+H10) | I11: =IF(OR(I9="",I10=""),"",I9+I10) | J11: =IF(OR(J9="",J10=""),"",J9+J10) | K11: =IF(OR(K9="",K10=""),"",K9+K10) | L11: =IF(OR(L9="",L10=""),"",L9+L10) | M11: =IF(OR(M9="",M10=""),"",M9+M10) | ... AO11: =IF(OR(AO9="",AO10=""),"",AO9+AO10) | AP11: =IF(COUNT(F11:Q11)=0,"",SUM(F11:Q11)) | AQ11: =IF(COUNT(R11:AC11)=0,"",SUM(R11:AC11)) | AR11: =IF(COUNT(AD11:AO11)=0,"",SUM(AD11:AO11))
A12: IS_OPEX | B12: Operating expenses | C12: + | D12: TB/Map | AP12: =IF(COUNT(F12:Q12)=0,"",SUM(F12:Q12)) | AQ12: =IF(COUNT(R12:AC12)=0,"",SUM(R12:AC12)) | AR12: =IF(COUNT(AD12:AO12)=0,"",SUM(AD12:AO12))
A13: IS_EBITDA | B13: EBITDA | C13: + | D13: Formula | E13: Derived | F13: =IF(OR(F11="",F12=""),"",F11+F12) | G13: =IF(OR(G11="",G12=""),"",G11+G12) | H13: =IF(OR(H11="",H12=""),"",H11+H12) | I13: =IF(OR(I11="",I12=""),"",I11+I12) | J13: =IF(OR(J11="",J12=""),"",J11+J12) | K13: =IF(OR(K11="",K12=""),"",K11+K12) | L13: =IF(OR(L11="",L12=""),"",L11+L12) | M13: =IF(OR(M11="",M12=""),"",M11+M12) | ... AO13: =IF(OR(AO11="",AO12=""),"",AO11+AO12) | AP13: =IF(COUNT(F13:Q13)=0,"",SUM(F13:Q13)) | AQ13: =IF(COUNT(R13:AC13)=0,"",SUM(R13:AC13)) | AR13: =IF(COUNT(AD13:AO13)=0,"",SUM(AD13:AO13))
A27: IS_CHECKS
A28: Gross profit tie-out | F28: =IF(F11="","",F11-(F9+F10)) | G28: =IF(G11="","",G11-(G9+G10)) | H28: =IF(H11="","",H11-(H9+H10)) | I28: =IF(I11="","",I11-(I9+I10)) | J28: =IF(J11="","",J11-(J9+J10)) | K28: =IF(K11="","",K11-(K9+K10)) | L28: =IF(L11="","",L11-(L9+L10)) | M28: =IF(M11="","",M11-(M9+M10)) | ... AR28: =IF(AR11="","",AR11-(AR9+AR10))
A29: EBITDA tie-out | F29: =IF(F13="","",F13-(F11+F12)) | G29: =IF(G13="","",G13-(G11+G12)) | H29: =IF(H13="","",H13-(H11+H12)) | I29: =IF(I13="","",I13-(I11+I12)) | J29: =IF(J13="","",J13-(J11+J12)) | K29: =IF(K13="","",K13-(K11+K12)) | L29: =IF(L13="","",L13-(L11+L12)) | M29: =IF(M13="","",M13-(M11+M12)) | ... AR29: =IF(AR13="","",AR13-(AR11+AR12))

Sheet Combined | BS
A1: Combined | BS (Template Scaffold)
A2: Combined BS scaffold with deterministic anchors and check block.
A4: Data as of | D4: Units | E4: ='Control | Setup'!B11
A5: Version | B5: ='Control | Setup'!B9 | D5: Last refresh | E5: ='Control | Setup'!B14
A8: LineKey | B8: LineName | C8: Sign | D8: Source | E8: Comments | F8: ='Control | Periods'!A9 | G8: ='Control | Periods'!A10 | H8: ='Control | Periods'!A11 | I8: ='Control | Periods'!A12 | J8: ='Control | Periods'!A13 | K8: ='Control | Periods'!A14 | L8: ='Control | Periods'!A15 | M8: ='Control | Periods'!A16 | N8: ='Control | Periods'!A17 | O8: ='Control | Periods'!A18 | P8: ='Control | Periods'!A19 | Q8: ='Control | Periods'!A20 | R8: ='Control | Periods'!A21 | S8: ='Control | Periods'!A22 | T8: ='Control | Periods'!A23 | U8: ='Control | Periods'!A24 | V8: ='Control | Periods'!A25 | W8: ='Control | Periods'!A26 | X8: ='Control | Periods'!A27 | Y8: ='Control | Periods'!A28 | Z8: ='Control | Periods'!A29 | AA8: ='Control | Periods'!A30 | AB8: ='Control | Periods'!A31 | AC8: ='Control | Periods'!A32 | AD8: ='Control | Periods'!A33 | AE8: ='Control | Periods'!A34 | AF8: ='Control | Periods'!A35 | AG8: ='Control | Periods'!A36 | AH8: ='Control | Periods'!A37 | AI8: ='Control | Periods'!A38 | AJ8: ='Control | Periods'!A39 | AK8: ='Control | Periods'!A40 | AL8: ='Control | Periods'!A41 | AM8: ='Control | Periods'!A42 | AN8: ='Control | Periods'!A43 | AO8: ='Control | Periods'!A44 | AP8: FY-2 | AQ8: FY-1 | AR8: TTM
A9: BS_CASH | B9: Cash | C9: + | D9: TB/Map | AP9: =Q9 | AQ9: =AC9 | AR9: =AO9
A10: BS_AR | B10: Accounts receivable | C10: + | D10: TB/Map | AP10: =Q10 | AQ10: =AC10 | AR10: =AO10
A11: BS_INV | B11: Inventory | C11: + | D11: TB/Map | AP11: =Q11 | AQ11: =AC11 | AR11: =AO11
A12: BS_OCA | B12: Other current assets | C12: + | D12: TB/Map | AP12: =Q12 | AQ12: =AC12 | AR12: =AO12
A13: BS_TCA | B13: Total current assets | C13: + | D13: Formula | E13: Derived | F13: =IF(COUNT(F9:F12)=0,"",SUM(F9:F12)) | G13: =IF(COUNT(G9:G12)=0,"",SUM(G9:G12)) | H13: =IF(COUNT(H9:H12)=0,"",SUM(H9:H12)) | I13: =IF(COUNT(I9:I12)=0,"",SUM(I9:I12)) | J13: =IF(COUNT(J9:J12)=0,"",SUM(J9:J12)) | K13: =IF(COUNT(K9:K12)=0,"",SUM(K9:K12)) | L13: =IF(COUNT(L9:L12)=0,"",SUM(L9:L12)) | M13: =IF(COUNT(M9:M12)=0,"",SUM(M9:M12)) | ... AO13: =IF(COUNT(AO9:AO12)=0,"",SUM(AO9:AO12)) | AP13: =Q13 | AQ13: =AC13 | AR13: =AO13
A14: BS_PPE | B14: PP&E | C14: + | D14: TB/Map | AP14: =Q14 | AQ14: =AC14 | AR14: =AO14
A15: BS_OTA | B15: Other assets | C15: + | D15: TB/Map | AP15: =Q15 | AQ15: =AC15 | AR15: =AO15
A16: BS_TA | B16: Total assets | C16: + | D16: Formula | E16: Derived | F16: =IF(COUNT(F13:F15)=0,"",SUM(F13:F15)) | G16: =IF(COUNT(G13:G15)=0,"",SUM(G13:G15)) | H16: =IF(COUNT(H13:H15)=0,"",SUM(H13:H15)) | I16: =IF(COUNT(I13:I15)=0,"",SUM(I13:I15)) | J16: =IF(COUNT(J13:J15)=0,"",SUM(J13:J15)) | K16: =IF(COUNT(K13:K15)=0,"",SUM(K13:K15)) | L16: =IF(COUNT(L13:L15)=0,"",SUM(L13:L15)) | M16: =IF(COUNT(M13:M15)=0,"",SUM(M13:M15)) | ... AO16: =IF(COUNT(AO13:AO15)=0,"",SUM(AO13:AO15)) | AP16: =Q16 | AQ16: =AC16 | AR16: =AO16
A17: BS_AP | B17: Accounts payable | C17: + | D17: TB/Map | AP17: =Q17 | AQ17: =AC17 | AR17: =AO17
A18: BS_ACCR | B18: Accrued liabilities | C18: + | D18: TB/Map | AP18: =Q18 | AQ18: =AC18 | AR18: =AO18
A19: BS_DEBT | B19: Debt | C19: + | D19: TB/Map | AP19: =Q19 | AQ19: =AC19 | AR19: =AO19
A20: BS_OL | B20: Other liabilities | C20: + | D20: TB/Map | AP20: =Q20 | AQ20: =AC20 | AR20: =AO20
A21: BS_TL | B21: Total liabilities | C21: + | D21: Formula | E21: Derived | AP21: =Q21 | AQ21: =AC21 | AR21: =AO21
A22: BS_EQ | B22: Equity | C22: + | D22: TB/Map | F22: =IF(COUNT(F17:F20)=0,"",SUM(F17:F20)) | G22: =IF(COUNT(G17:G20)=0,"",SUM(G17:G20)) | H22: =IF(COUNT(H17:H20)=0,"",SUM(H17:H20)) | I22: =IF(COUNT(I17:I20)=0,"",SUM(I17:I20)) | J22: =IF(COUNT(J17:J20)=0,"",SUM(J17:J20)) | K22: =IF(COUNT(K17:K20)=0,"",SUM(K17:K20)) | L22: =IF(COUNT(L17:L20)=0,"",SUM(L17:L20)) | M22: =IF(COUNT(M17:M20)=0,"",SUM(M17:M20)) | ... AO22: =IF(COUNT(AO17:AO20)=0,"",SUM(AO17:AO20)) | AP22: =Q22 | AQ22: =AC22 | AR22: =AO22
A23: BS_TLE | B23: Total liabilities + equity | C23: + | D23: Formula | E23: Derived | AP23: =Q23 | AQ23: =AC23 | AR23: =AO23
F24: =IF(COUNT(F22:F23)=0,"",SUM(F22:F23)) | G24: =IF(COUNT(G22:G23)=0,"",SUM(G22:G23)) | H24: =IF(COUNT(H22:H23)=0,"",SUM(H22:H23)) | I24: =IF(COUNT(I22:I23)=0,"",SUM(I22:I23)) | J24: =IF(COUNT(J22:J23)=0,"",SUM(J22:J23)) | K24: =IF(COUNT(K22:K23)=0,"",SUM(K22:K23)) | L24: =IF(COUNT(L22:L23)=0,"",SUM(L22:L23)) | M24: =IF(COUNT(M22:M23)=0,"",SUM(M22:M23)) | ... AO24: =IF(COUNT(AO22:AO23)=0,"",SUM(AO22:AO23)) | AP24: =Q24 | AQ24: =AC24 | AR24: =AO24
A27: BS_CHECKS
A28: Balance check (Assets - Liab&Eq) | F28: =IF(OR(F16="",F24=""),"",F16-F24) | G28: =IF(OR(G16="",G24=""),"",G16-G24) | H28: =IF(OR(H16="",H24=""),"",H16-H24) | I28: =IF(OR(I16="",I24=""),"",I16-I24) | J28: =IF(OR(J16="",J24=""),"",J16-J24) | K28: =IF(OR(K16="",K24=""),"",K16-K24) | L28: =IF(OR(L16="",L24=""),"",L16-L24) | M28: =IF(OR(M16="",M24=""),"",M16-M24) | ... AR28: =IF(OR(AR16="",AR24=""),"",AR16-AR24)

Sheet Combined | CF
A1: Combined | CF (Template Scaffold)
A2: Combined CF scaffold with deterministic anchors and check block.
A4: Data as of | D4: Units | E4: ='Control | Setup'!B11
A5: Version | B5: ='Control | Setup'!B9 | D5: Last refresh | E5: ='Control | Setup'!B14
A8: LineKey | B8: LineName | C8: Sign | D8: Source | E8: Comments | F8: ='Control | Periods'!A9 | G8: ='Control | Periods'!A10 | H8: ='Control | Periods'!A11 | I8: ='Control | Periods'!A12 | J8: ='Control | Periods'!A13 | K8: ='Control | Periods'!A14 | L8: ='Control | Periods'!A15 | M8: ='Control | Periods'!A16 | N8: ='Control | Periods'!A17 | O8: ='Control | Periods'!A18 | P8: ='Control | Periods'!A19 | Q8: ='Control | Periods'!A20 | R8: ='Control | Periods'!A21 | S8: ='Control | Periods'!A22 | T8: ='Control | Periods'!A23 | U8: ='Control | Periods'!A24 | V8: ='Control | Periods'!A25 | W8: ='Control | Periods'!A26 | X8: ='Control | Periods'!A27 | Y8: ='Control | Periods'!A28 | Z8: ='Control | Periods'!A29 | AA8: ='Control | Periods'!A30 | AB8: ='Control | Periods'!A31 | AC8: ='Control | Periods'!A32 | AD8: ='Control | Periods'!A33 | AE8: ='Control | Periods'!A34 | AF8: ='Control | Periods'!A35 | AG8: ='Control | Periods'!A36 | AH8: ='Control | Periods'!A37 | AI8: ='Control | Periods'!A38 | AJ8: ='Control | Periods'!A39 | AK8: ='Control | Periods'!A40 | AL8: ='Control | Periods'!A41 | AM8: ='Control | Periods'!A42 | AN8: ='Control | Periods'!A43 | AO8: ='Control | Periods'!A44 | AP8: FY-2 | AQ8: FY-1 | AR8: TTM
A9: CF_EBITDA | B9: EBITDA | C9: + | D9: Link/Map | AP9: =IF(COUNT(F9:Q9)=0,"",SUM(F9:Q9)) | AQ9: =IF(COUNT(R9:AC9)=0,"",SUM(R9:AC9)) | AR9: =IF(COUNT(AD9:AO9)=0,"",SUM(AD9:AO9))
A10: CF_CHG_NWC | B10: Change in NWC | C10: + | D10: Link/Map | AP10: =IF(COUNT(F10:Q10)=0,"",SUM(F10:Q10)) | AQ10: =IF(COUNT(R10:AC10)=0,"",SUM(R10:AC10)) | AR10: =IF(COUNT(AD10:AO10)=0,"",SUM(AD10:AO10))
A11: CF_CAPEX | B11: Capex | C11: + | D11: Link/Map | AP11: =IF(COUNT(F11:Q11)=0,"",SUM(F11:Q11)) | AQ11: =IF(COUNT(R11:AC11)=0,"",SUM(R11:AC11)) | AR11: =IF(COUNT(AD11:AO11)=0,"",SUM(AD11:AO11))
A12: CF_OTHER | B12: Other | C12: + | D12: Link/Map | AP12: =IF(COUNT(F12:Q12)=0,"",SUM(F12:Q12)) | AQ12: =IF(COUNT(R12:AC12)=0,"",SUM(R12:AC12)) | AR12: =IF(COUNT(AD12:AO12)=0,"",SUM(AD12:AO12))
A13: CF_NET | B13: Net cash flow | C13: + | D13: Formula | E13: Derived | F13: =IF(COUNT(F9:F12)=0,"",SUM(F9:F12)) | G13: =IF(COUNT(G9:G12)=0,"",SUM(G9:G12)) | H13: =IF(COUNT(H9:H12)=0,"",SUM(H9:H12)) | I13: =IF(COUNT(I9:I12)=0,"",SUM(I9:I12)) | J13: =IF(COUNT(J9:J12)=0,"",SUM(J9:J12)) | K13: =IF(COUNT(K9:K12)=0,"",SUM(K9:K12)) | L13: =IF(COUNT(L9:L12)=0,"",SUM(L9:L12)) | M13: =IF(COUNT(M9:M12)=0,"",SUM(M9:M12)) | ... AO13: =IF(COUNT(AO9:AO12)=0,"",SUM(AO9:AO12)) | AP13: =IF(COUNT(F13:Q13)=0,"",SUM(F13:Q13)) | AQ13: =IF(COUNT(R13:AC13)=0,"",SUM(R13:AC13)) | AR13: =IF(COUNT(AD13:AO13)=0,"",SUM(AD13:AO13))
A27: CF_CHECKS
A28: Net cash tie-out | F28: =IF(F13="","",F13-SUM(F9:F12)) | G28: =IF(G13="","",G13-SUM(G9:G12)) | H28: =IF(H13="","",H13-SUM(H9:H12)) | I28: =IF(I13="","",I13-SUM(I9:I12)) | J28: =IF(J13="","",J13-SUM(J9:J12)) | K28: =IF(K13="","",K13-SUM(K9:K12)) | L28: =IF(L13="","",L13-SUM(L9:L12)) | M28: =IF(M13="","",M13-SUM(M9:M12)) | ... AR28: =IF(AR13="","",AR13-SUM(AR9:AR12))

Sheet Entity 1 | IS
A1: Entity 1 | IS (Template Scaffold)
A2: Entity 1 placeholder IS scaffold with deterministic anchors and check block.
A4: Data as of | D4: Units | E4: ='Control | Setup'!B11
A5: Version | B5: ='Control | Setup'!B9 | D5: Last refresh | E5: ='Control | Setup'!B14
A8: LineKey | B8: LineName | C8: Sign | D8: Source | E8: Comments | F8: ='Control | Periods'!A9 | G8: ='Control | Periods'!A10 | H8: ='Control | Periods'!A11 | I8: ='Control | Periods'!A12 | J8: ='Control | Periods'!A13 | K8: ='Control | Periods'!A14 | L8: ='Control | Periods'!A15 | M8: ='Control | Periods'!A16 | N8: ='Control | Periods'!A17 | O8: ='Control | Periods'!A18 | P8: ='Control | Periods'!A19 | Q8: ='Control | Periods'!A20 | R8: ='Control | Periods'!A21 | S8: ='Control | Periods'!A22 | T8: ='Control | Periods'!A23 | U8: ='Control | Periods'!A24 | V8: ='Control | Periods'!A25 | W8: ='Control | Periods'!A26 | X8: ='Control | Periods'!A27 | Y8: ='Control | Periods'!A28 | Z8: ='Control | Periods'!A29 | AA8: ='Control | Periods'!A30 | AB8: ='Control | Periods'!A31 | AC8: ='Control | Periods'!A32 | AD8: ='Control | Periods'!A33 | AE8: ='Control | Periods'!A34 | AF8: ='Control | Periods'!A35 | AG8: ='Control | Periods'!A36 | AH8: ='Control | Periods'!A37 | AI8: ='Control | Periods'!A38 | AJ8: ='Control | Periods'!A39 | AK8: ='Control | Periods'!A40 | AL8: ='Control | Periods'!A41 | AM8: ='Control | Periods'!A42 | AN8: ='Control | Periods'!A43 | AO8: ='Control | Periods'!A44 | AP8: FY-2 | AQ8: FY-1 | AR8: TTM
A9: IS_REV | B9: Revenue | C9: + | D9: TB/Map | AP9: =IF(COUNT(F9:Q9)=0,"",SUM(F9:Q9)) | AQ9: =IF(COUNT(R9:AC9)=0,"",SUM(R9:AC9)) | AR9: =IF(COUNT(AD9:AO9)=0,"",SUM(AD9:AO9))
A10: IS_COGS | B10: Cost of goods sold | C10: + | D10: TB/Map | AP10: =IF(COUNT(F10:Q10)=0,"",SUM(F10:Q10)) | AQ10: =IF(COUNT(R10:AC10)=0,"",SUM(R10:AC10)) | AR10: =IF(COUNT(AD10:AO10)=0,"",SUM(AD10:AO10))
A11: IS_GP | B11: Gross profit | C11: + | D11: Formula | E11: Derived | F11: =IF(OR(F9="",F10=""),"",F9+F10) | G11: =IF(OR(G9="",G10=""),"",G9+G10) | H11: =IF(OR(H9="",H10=""),"",H9+H10) | I11: =IF(OR(I9="",I10=""),"",I9+I10) | J11: =IF(OR(J9="",J10=""),"",J9+J10) | K11: =IF(OR(K9="",K10=""),"",K9+K10) | L11: =IF(OR(L9="",L10=""),"",L9+L10) | M11: =IF(OR(M9="",M10=""),"",M9+M10) | ... AO11: =IF(OR(AO9="",AO10=""),"",AO9+AO10) | AP11: =IF(COUNT(F11:Q11)=0,"",SUM(F11:Q11)) | AQ11: =IF(COUNT(R11:AC11)=0,"",SUM(R11:AC11)) | AR11: =IF(COUNT(AD11:AO11)=0,"",SUM(AD11:AO11))
A12: IS_OPEX | B12: Operating expenses | C12: + | D12: TB/Map | AP12: =IF(COUNT(F12:Q12)=0,"",SUM(F12:Q12)) | AQ12: =IF(COUNT(R12:AC12)=0,"",SUM(R12:AC12)) | AR12: =IF(COUNT(AD12:AO12)=0,"",SUM(AD12:AO12))
A13: IS_EBITDA | B13: EBITDA | C13: + | D13: Formula | E13: Derived | F13: =IF(OR(F11="",F12=""),"",F11+F12) | G13: =IF(OR(G11="",G12=""),"",G11+G12) | H13: =IF(OR(H11="",H12=""),"",H11+H12) | I13: =IF(OR(I11="",I12=""),"",I11+I12) | J13: =IF(OR(J11="",J12=""),"",J11+J12) | K13: =IF(OR(K11="",K12=""),"",K11+K12) | L13: =IF(OR(L11="",L12=""),"",L11+L12) | M13: =IF(OR(M11="",M12=""),"",M11+M12) | ... AO13: =IF(OR(AO11="",AO12=""),"",AO11+AO12) | AP13: =IF(COUNT(F13:Q13)=0,"",SUM(F13:Q13)) | AQ13: =IF(COUNT(R13:AC13)=0,"",SUM(R13:AC13)) | AR13: =IF(COUNT(AD13:AO13)=0,"",SUM(AD13:AO13))
A27: IS_CHECKS
A28: Gross profit tie-out | F28: =IF(F11="","",F11-(F9+F10)) | G28: =IF(G11="","",G11-(G9+G10)) | H28: =IF(H11="","",H11-(H9+H10)) | I28: =IF(I11="","",I11-(I9+I10)) | J28: =IF(J11="","",J11-(J9+J10)) | K28: =IF(K11="","",K11-(K9+K10)) | L28: =IF(L11="","",L11-(L9+L10)) | M28: =IF(M11="","",M11-(M9+M10)) | ... AR28: =IF(AR11="","",AR11-(AR9+AR10))
A29: EBITDA tie-out | F29: =IF(F13="","",F13-(F11+F12)) | G29: =IF(G13="","",G13-(G11+G12)) | H29: =IF(H13="","",H13-(H11+H12)) | I29: =IF(I13="","",I13-(I11+I12)) | J29: =IF(J13="","",J13-(J11+J12)) | K29: =IF(K13="","",K13-(K11+K12)) | L29: =IF(L13="","",L13-(L11+L12)) | M29: =IF(M13="","",M13-(M11+M12)) | ... AR29: =IF(AR13="","",AR13-(AR11+AR12))

Sheet Entity 1 | BS
A1: Entity 1 | BS (Template Scaffold)
A2: Entity 1 placeholder BS scaffold with deterministic anchors and check block.
A4: Data as of | D4: Units | E4: ='Control | Setup'!B11
A5: Version | B5: ='Control | Setup'!B9 | D5: Last refresh | E5: ='Control | Setup'!B14
A8: LineKey | B8: LineName | C8: Sign | D8: Source | E8: Comments | F8: ='Control | Periods'!A9 | G8: ='Control | Periods'!A10 | H8: ='Control | Periods'!A11 | I8: ='Control | Periods'!A12 | J8: ='Control | Periods'!A13 | K8: ='Control | Periods'!A14 | L8: ='Control | Periods'!A15 | M8: ='Control | Periods'!A16 | N8: ='Control | Periods'!A17 | O8: ='Control | Periods'!A18 | P8: ='Control | Periods'!A19 | Q8: ='Control | Periods'!A20 | R8: ='Control | Periods'!A21 | S8: ='Control | Periods'!A22 | T8: ='Control | Periods'!A23 | U8: ='Control | Periods'!A24 | V8: ='Control | Periods'!A25 | W8: ='Control | Periods'!A26 | X8: ='Control | Periods'!A27 | Y8: ='Control | Periods'!A28 | Z8: ='Control | Periods'!A29 | AA8: ='Control | Periods'!A30 | AB8: ='Control | Periods'!A31 | AC8: ='Control | Periods'!A32 | AD8: ='Control | Periods'!A33 | AE8: ='Control | Periods'!A34 | AF8: ='Control | Periods'!A35 | AG8: ='Control | Periods'!A36 | AH8: ='Control | Periods'!A37 | AI8: ='Control | Periods'!A38 | AJ8: ='Control | Periods'!A39 | AK8: ='Control | Periods'!A40 | AL8: ='Control | Periods'!A41 | AM8: ='Control | Periods'!A42 | AN8: ='Control | Periods'!A43 | AO8: ='Control | Periods'!A44 | AP8: FY-2 | AQ8: FY-1 | AR8: TTM
A9: BS_CASH | B9: Cash | C9: + | D9: TB/Map | AP9: =Q9 | AQ9: =AC9 | AR9: =AO9
A10: BS_AR | B10: Accounts receivable | C10: + | D10: TB/Map | AP10: =Q10 | AQ10: =AC10 | AR10: =AO10
A11: BS_INV | B11: Inventory | C11: + | D11: TB/Map | AP11: =Q11 | AQ11: =AC11 | AR11: =AO11
A12: BS_OCA | B12: Other current assets | C12: + | D12: TB/Map | AP12: =Q12 | AQ12: =AC12 | AR12: =AO12
A13: BS_TCA | B13: Total current assets | C13: + | D13: Formula | E13: Derived | F13: =IF(COUNT(F9:F12)=0,"",SUM(F9:F12)) | G13: =IF(COUNT(G9:G12)=0,"",SUM(G9:G12)) | H13: =IF(COUNT(H9:H12)=0,"",SUM(H9:H12)) | I13: =IF(COUNT(I9:I12)=0,"",SUM(I9:I12)) | J13: =IF(COUNT(J9:J12)=0,"",SUM(J9:J12)) | K13: =IF(COUNT(K9:K12)=0,"",SUM(K9:K12)) | L13: =IF(COUNT(L9:L12)=0,"",SUM(L9:L12)) | M13: =IF(COUNT(M9:M12)=0,"",SUM(M9:M12)) | ... AO13: =IF(COUNT(AO9:AO12)=0,"",SUM(AO9:AO12)) | AP13: =Q13 | AQ13: =AC13 | AR13: =AO13
A14: BS_PPE | B14: PP&E | C14: + | D14: TB/Map | AP14: =Q14 | AQ14: =AC14 | AR14: =AO14
A15: BS_OTA | B15: Other assets | C15: + | D15: TB/Map | AP15: =Q15 | AQ15: =AC15 | AR15: =AO15
A16: BS_TA | B16: Total assets | C16: + | D16: Formula | E16: Derived | F16: =IF(COUNT(F13:F15)=0,"",SUM(F13:F15)) | G16: =IF(COUNT(G13:G15)=0,"",SUM(G13:G15)) | H16: =IF(COUNT(H13:H15)=0,"",SUM(H13:H15)) | I16: =IF(COUNT(I13:I15)=0,"",SUM(I13:I15)) | J16: =IF(COUNT(J13:J15)=0,"",SUM(J13:J15)) | K16: =IF(COUNT(K13:K15)=0,"",SUM(K13:K15)) | L16: =IF(COUNT(L13:L15)=0,"",SUM(L13:L15)) | M16: =IF(COUNT(M13:M15)=0,"",SUM(M13:M15)) | ... AO16: =IF(COUNT(AO13:AO15)=0,"",SUM(AO13:AO15)) | AP16: =Q16 | AQ16: =AC16 | AR16: =AO16
A17: BS_AP | B17: Accounts payable | C17: + | D17: TB/Map | AP17: =Q17 | AQ17: =AC17 | AR17: =AO17
A18: BS_ACCR | B18: Accrued liabilities | C18: + | D18: TB/Map | AP18: =Q18 | AQ18: =AC18 | AR18: =AO18
A19: BS_DEBT | B19: Debt | C19: + | D19: TB/Map | AP19: =Q19 | AQ19: =AC19 | AR19: =AO19
A20: BS_OL | B20: Other liabilities | C20: + | D20: TB/Map | AP20: =Q20 | AQ20: =AC20 | AR20: =AO20
A21: BS_TL | B21: Total liabilities | C21: + | D21: Formula | E21: Derived | AP21: =Q21 | AQ21: =AC21 | AR21: =AO21
A22: BS_EQ | B22: Equity | C22: + | D22: TB/Map | F22: =IF(COUNT(F17:F20)=0,"",SUM(F17:F20)) | G22: =IF(COUNT(G17:G20)=0,"",SUM(G17:G20)) | H22: =IF(COUNT(H17:H20)=0,"",SUM(H17:H20)) | I22: =IF(COUNT(I17:I20)=0,"",SUM(I17:I20)) | J22: =IF(COUNT(J17:J20)=0,"",SUM(J17:J20)) | K22: =IF(COUNT(K17:K20)=0,"",SUM(K17:K20)) | L22: =IF(COUNT(L17:L20)=0,"",SUM(L17:L20)) | M22: =IF(COUNT(M17:M20)=0,"",SUM(M17:M20)) | ... AO22: =IF(COUNT(AO17:AO20)=0,"",SUM(AO17:AO20)) | AP22: =Q22 | AQ22: =AC22 | AR22: =AO22
A23: BS_TLE | B23: Total liabilities + equity | C23: + | D23: Formula | E23: Derived | AP23: =Q23 | AQ23: =AC23 | AR23: =AO23
F24: =IF(COUNT(F22:F23)=0,"",SUM(F22:F23)) | G24: =IF(COUNT(G22:G23)=0,"",SUM(G22:G23)) | H24: =IF(COUNT(H22:H23)=0,"",SUM(H22:H23)) | I24: =IF(COUNT(I22:I23)=0,"",SUM(I22:I23)) | J24: =IF(COUNT(J22:J23)=0,"",SUM(J22:J23)) | K24: =IF(COUNT(K22:K23)=0,"",SUM(K22:K23)) | L24: =IF(COUNT(L22:L23)=0,"",SUM(L22:L23)) | M24: =IF(COUNT(M22:M23)=0,"",SUM(M22:M23)) | ... AO24: =IF(COUNT(AO22:AO23)=0,"",SUM(AO22:AO23)) | AP24: =Q24 | AQ24: =AC24 | AR24: =AO24
A27: BS_CHECKS
A28: Balance check (Assets - Liab&Eq) | F28: =IF(OR(F16="",F24=""),"",F16-F24) | G28: =IF(OR(G16="",G24=""),"",G16-G24) | H28: =IF(OR(H16="",H24=""),"",H16-H24) | I28: =IF(OR(I16="",I24=""),"",I16-I24) | J28: =IF(OR(J16="",J24=""),"",J16-J24) | K28: =IF(OR(K16="",K24=""),"",K16-K24) | L28: =IF(OR(L16="",L24=""),"",L16-L24) | M28: =IF(OR(M16="",M24=""),"",M16-M24) | ... AR28: =IF(OR(AR16="",AR24=""),"",AR16-AR24)

Sheet Entity 1 | CF
A1: Entity 1 | CF (Template Scaffold)
A2: Entity 1 placeholder CF scaffold with deterministic anchors and check block.
A4: Data as of | D4: Units | E4: ='Control | Setup'!B11
A5: Version | B5: ='Control | Setup'!B9 | D5: Last refresh | E5: ='Control | Setup'!B14
A8: LineKey | B8: LineName | C8: Sign | D8: Source | E8: Comments | F8: ='Control | Periods'!A9 | G8: ='Control | Periods'!A10 | H8: ='Control | Periods'!A11 | I8: ='Control | Periods'!A12 | J8: ='Control | Periods'!A13 | K8: ='Control | Periods'!A14 | L8: ='Control | Periods'!A15 | M8: ='Control | Periods'!A16 | N8: ='Control | Periods'!A17 | O8: ='Control | Periods'!A18 | P8: ='Control | Periods'!A19 | Q8: ='Control | Periods'!A20 | R8: ='Control | Periods'!A21 | S8: ='Control | Periods'!A22 | T8: ='Control | Periods'!A23 | U8: ='Control | Periods'!A24 | V8: ='Control | Periods'!A25 | W8: ='Control | Periods'!A26 | X8: ='Control | Periods'!A27 | Y8: ='Control | Periods'!A28 | Z8: ='Control | Periods'!A29 | AA8: ='Control | Periods'!A30 | AB8: ='Control | Periods'!A31 | AC8: ='Control | Periods'!A32 | AD8: ='Control | Periods'!A33 | AE8: ='Control | Periods'!A34 | AF8: ='Control | Periods'!A35 | AG8: ='Control | Periods'!A36 | AH8: ='Control | Periods'!A37 | AI8: ='Control | Periods'!A38 | AJ8: ='Control | Periods'!A39 | AK8: ='Control | Periods'!A40 | AL8: ='Control | Periods'!A41 | AM8: ='Control | Periods'!A42 | AN8: ='Control | Periods'!A43 | AO8: ='Control | Periods'!A44 | AP8: FY-2 | AQ8: FY-1 | AR8: TTM
A9: CF_EBITDA | B9: EBITDA | C9: + | D9: Link/Map | AP9: =IF(COUNT(F9:Q9)=0,"",SUM(F9:Q9)) | AQ9: =IF(COUNT(R9:AC9)=0,"",SUM(R9:AC9)) | AR9: =IF(COUNT(AD9:AO9)=0,"",SUM(AD9:AO9))
A10: CF_CHG_NWC | B10: Change in NWC | C10: + | D10: Link/Map | AP10: =IF(COUNT(F10:Q10)=0,"",SUM(F10:Q10)) | AQ10: =IF(COUNT(R10:AC10)=0,"",SUM(R10:AC10)) | AR10: =IF(COUNT(AD10:AO10)=0,"",SUM(AD10:AO10))
A11: CF_CAPEX | B11: Capex | C11: + | D11: Link/Map | AP11: =IF(COUNT(F11:Q11)=0,"",SUM(F11:Q11)) | AQ11: =IF(COUNT(R11:AC11)=0,"",SUM(R11:AC11)) | AR11: =IF(COUNT(AD11:AO11)=0,"",SUM(AD11:AO11))
A12: CF_OTHER | B12: Other | C12: + | D12: Link/Map | AP12: =IF(COUNT(F12:Q12)=0,"",SUM(F12:Q12)) | AQ12: =IF(COUNT(R12:AC12)=0,"",SUM(R12:AC12)) | AR12: =IF(COUNT(AD12:AO12)=0,"",SUM(AD12:AO12))
A13: CF_NET | B13: Net cash flow | C13: + | D13: Formula | E13: Derived | F13: =IF(COUNT(F9:F12)=0,"",SUM(F9:F12)) | G13: =IF(COUNT(G9:G12)=0,"",SUM(G9:G12)) | H13: =IF(COUNT(H9:H12)=0,"",SUM(H9:H12)) | I13: =IF(COUNT(I9:I12)=0,"",SUM(I9:I12)) | J13: =IF(COUNT(J9:J12)=0,"",SUM(J9:J12)) | K13: =IF(COUNT(K9:K12)=0,"",SUM(K9:K12)) | L13: =IF(COUNT(L9:L12)=0,"",SUM(L9:L12)) | M13: =IF(COUNT(M9:M12)=0,"",SUM(M9:M12)) | ... AO13: =IF(COUNT(AO9:AO12)=0,"",SUM(AO9:AO12)) | AP13: =IF(COUNT(F13:Q13)=0,"",SUM(F13:Q13)) | AQ13: =IF(COUNT(R13:AC13)=0,"",SUM(R13:AC13)) | AR13: =IF(COUNT(AD13:AO13)=0,"",SUM(AD13:AO13))
A27: CF_CHECKS
A28: Net cash tie-out | F28: =IF(F13="","",F13-SUM(F9:F12)) | G28: =IF(G13="","",G13-SUM(G9:G12)) | H28: =IF(H13="","",H13-SUM(H9:H12)) | I28: =IF(I13="","",I13-SUM(I9:I12)) | J28: =IF(J13="","",J13-SUM(J9:J12)) | K28: =IF(K13="","",K13-SUM(K9:K12)) | L28: =IF(L13="","",L13-SUM(L9:L12)) | M28: =IF(M13="","",M13-SUM(M9:M12)) | ... AR28: =IF(AR13="","",AR13-SUM(AR9:AR12))
